{
  "strategy": "Optimized Stochastic RSI",
  "parameters": {
    "rsi_period": 14,
    "stoch_period": 14,
    "k_period": 3,
    "d_period": 3,
    "overbought": 75,
    "oversold": 25,
    "timeframe": "1h",
    "period_days": 720,
    "risk_per_trade": 0.015,
    "stop_loss_pct": 0.02,
    "take_profit_pct": 0.05
  },
  "pairs": [
    "EURUSD",
    "GBPUSD",
    "USDCAD",
    "EURGBP",
    "EURJPY",
    "AUDUSD",
    "GBPCAD"
  ],
  "overall_results": {
    "total_trades": 55,
    "winning_trades": 21,
    "win_rate": 38.18181818181819,
    "avg_win": 7.491778806428907,
    "avg_loss": -3.30128187670852,
    "profit_factor": 1.4016601180874628,
    "net_pnl": 45.08377112691735
  },
  "pair_results": {
    "EURUSD": {
      "trades": 7,
      "winning_trades": 4,
      "win_rate": 57.14285714285714
    },
    "GBPUSD": {
      "trades": 7,
      "winning_trades": 4,
      "win_rate": 57.14285714285714
    },
    "USDCAD": {
      "trades": 9,
      "winning_trades": 1,
      "win_rate": 11.11111111111111
    },
    "EURGBP": {
      "trades": 3,
      "winning_trades": 0,
      "win_rate": 0.0
    },
    "EURJPY": {
      "trades": 11,
      "winning_trades": 5,
      "win_rate": 45.45454545454545
    },
    "AUDUSD": {
      "trades": 12,
      "winning_trades": 5,
      "win_rate": 41.66666666666667
    },
    "GBPCAD": {
      "trades": 6,
      "winning_trades": 2,
      "win_rate": 33.33333333333333
    }
  },
  "trades": [
    {
      "pair": "EURUSD",
      "entry_time": "2023-11-21 22:00:00+00:00",
      "exit_time": "2024-04-12 17:00:00+00:00",
      "entry_price": 1.0913456678390503,
      "exit_price": 1.0649627447128296,
      "position": "long",
      "pnl": -3.6262007405675076,
      "pnl_pct": -0.036262007405675076
    },
    {
      "pair": "EURUSD",
      "entry_time": "2024-04-12 17:00:00+00:00",
      "exit_time": "2024-09-25 04:00:00+00:00",
      "entry_price": 1.0649627447128296,
      "exit_price": 1.1199462413787842,
      "position": "long",
      "pnl": 7.741617087432871,
      "pnl_pct": 0.07744425371534625
    },
    {
      "pair": "EURUSD",
      "entry_time": "2024-09-25 04:00:00+00:00",
      "exit_time": "2024-11-13 07:00:00+00:00",
      "entry_price": 1.1199462413787842,
      "exit_price": 1.0605578422546387,
      "position": "short",
      "pnl": 7.957458723624764,
      "pnl_pct": 0.07954185245226343
    },
    {
      "pair": "EURUSD",
      "entry_time": "2024-11-13 07:00:00+00:00",
      "exit_time": "2025-03-10 09:00:00+00:00",
      "entry_price": 1.0605578422546387,
      "exit_price": 1.0854227542877197,
      "position": "short",
      "pnl": -3.5210146215813687,
      "pnl_pct": -0.03516768870458885
    },
    {
      "pair": "EURUSD",
      "entry_time": "2025-03-10 09:00:00+00:00",
      "exit_time": "2025-04-21 06:00:00+00:00",
      "entry_price": 1.0854227542877197,
      "exit_price": 1.1519410610198975,
      "position": "long",
      "pnl": 9.200358845919867,
      "pnl_pct": 0.0919249755029716
    },
    {
      "pair": "EURUSD",
      "entry_time": "2025-04-21 06:00:00+00:00",
      "exit_time": "2025-07-01 04:00:00+00:00",
      "entry_price": 1.1519410610198975,
      "exit_price": 1.1789672374725342,
      "position": "short",
      "pnl": -3.52546082823562,
      "pnl_pct": -0.03519213443356443
    },
    {
      "pair": "EURUSD",
      "entry_time": "2025-07-01 04:00:00+00:00",
      "exit_time": "2025-11-06 15:00:00+00:00",
      "entry_price": 1.1789672374725342,
      "exit_price": 1.1528706550598145,
      "position": "short",
      "pnl": 3.3249918097245867,
      "pnl_pct": 0.033202681444310725
    },
    {
      "pair": "GBPUSD",
      "entry_time": "2023-11-22 01:00:00+00:00",
      "exit_time": "2024-08-23 18:00:00+00:00",
      "entry_price": 1.2536512613296509,
      "exit_price": 1.3202714920043945,
      "position": "long",
      "pnl": 7.97114389739672,
      "pnl_pct": 0.0797114389739672
    },
    {
      "pair": "GBPUSD",
      "entry_time": "2024-08-23 18:00:00+00:00",
      "exit_time": "2024-12-20 05:00:00+00:00",
      "entry_price": 1.3202714920043945,
      "exit_price": 1.248688817024231,
      "position": "short",
      "pnl": 8.1392048901645,
      "pnl_pct": 0.08132722180286837
    },
    {
      "pair": "GBPUSD",
      "entry_time": "2024-12-20 05:00:00+00:00",
      "exit_time": "2025-01-13 05:00:00+00:00",
      "entry_price": 1.248688817024231,
      "exit_price": 1.2147420644760132,
      "position": "long",
      "pnl": -4.084457410889144,
      "pnl_pct": -0.04077887791425503
    },
    {
      "pair": "GBPUSD",
      "entry_time": "2025-01-13 05:00:00+00:00",
      "exit_time": "2025-03-06 17:00:00+00:00",
      "entry_price": 1.2147420644760132,
      "exit_price": 1.2888922691345215,
      "position": "long",
      "pnl": 9.167301321850173,
      "pnl_pct": 0.09156290066874419
    },
    {
      "pair": "GBPUSD",
      "entry_time": "2025-03-06 17:00:00+00:00",
      "exit_time": "2025-05-26 21:00:00+00:00",
      "entry_price": 1.2888922691345215,
      "exit_price": 1.3566128015518188,
      "position": "long",
      "pnl": 7.897951070672188,
      "pnl_pct": 0.07881248189513664
    },
    {
      "pair": "GBPUSD",
      "entry_time": "2025-05-26 21:00:00+00:00",
      "exit_time": "2025-07-31 01:00:00+00:00",
      "entry_price": 1.3566128015518188,
      "exit_price": 1.3257148265838623,
      "position": "long",
      "pnl": -3.426312284062197,
      "pnl_pct": -0.03416373662324201
    },
    {
      "pair": "GBPUSD",
      "entry_time": "2025-07-31 01:00:00+00:00",
      "exit_time": "2025-11-06 15:00:00+00:00",
      "entry_price": 1.3257148265838623,
      "exit_price": 1.3090033531188965,
      "position": "long",
      "pnl": -1.8956976467375242,
      "pnl_pct": -0.01890844825356792
    },
    {
      "pair": "USDCAD",
      "entry_time": "2023-11-23 08:00:00+00:00",
      "exit_time": "2023-12-18 03:00:00+00:00",
      "entry_price": 1.366510033607483,
      "exit_price": 1.337820053100586,
      "position": "long",
      "pnl": -3.149261234967766,
      "pnl_pct": -0.031492612349677665
    },
    {
      "pair": "USDCAD",
      "entry_time": "2023-12-18 03:00:00+00:00",
      "exit_time": "2024-04-11 01:00:00+00:00",
      "entry_price": 1.337820053100586,
      "exit_price": 1.3684200048446655,
      "position": "short",
      "pnl": -3.4298687946484603,
      "pnl_pct": -0.0343094929020834
    },
    {
      "pair": "USDCAD",
      "entry_time": "2024-04-11 01:00:00+00:00",
      "exit_time": "2024-11-14 07:00:00+00:00",
      "entry_price": 1.3684200048446655,
      "exit_price": 1.399780035018921,
      "position": "short",
      "pnl": -3.435282796036138,
      "pnl_pct": -0.03437544401195943
    },
    {
      "pair": "USDCAD",
      "entry_time": "2024-11-14 07:00:00+00:00",
      "exit_time": "2024-12-17 18:00:00+00:00",
      "entry_price": 1.399780035018921,
      "exit_price": 1.4308300018310547,
      "position": "short",
      "pnl": -3.3239728368957504,
      "pnl_pct": -0.03327304937419766
    },
    {
      "pair": "USDCAD",
      "entry_time": "2024-12-17 18:00:00+00:00",
      "exit_time": "2025-02-03 08:00:00+00:00",
      "entry_price": 1.4308300018310547,
      "exit_price": 1.4694900512695312,
      "position": "short",
      "pnl": -4.047491643747442,
      "pnl_pct": -0.04052897554811129
    },
    {
      "pair": "USDCAD",
      "entry_time": "2025-02-03 08:00:00+00:00",
      "exit_time": "2025-04-11 03:00:00+00:00",
      "entry_price": 1.4694900512695312,
      "exit_price": 1.3949300050735474,
      "position": "short",
      "pnl": 7.597576140461445,
      "pnl_pct": 0.07610808198215036
    },
    {
      "pair": "USDCAD",
      "entry_time": "2025-04-11 03:00:00+00:00",
      "exit_time": "2025-06-06 05:00:00+00:00",
      "entry_price": 1.3949300050735474,
      "exit_price": 1.3662999868392944,
      "position": "long",
      "pnl": -3.07563758104037,
      "pnl_pct": -0.030786510574138178
    },
    {
      "pair": "USDCAD",
      "entry_time": "2025-06-06 05:00:00+00:00",
      "exit_time": "2025-09-26 02:00:00+00:00",
      "entry_price": 1.3662999868392944,
      "exit_price": 1.394260048866272,
      "position": "short",
      "pnl": -3.0656621507090684,
      "pnl_pct": -0.030696108793419278
    },
    {
      "pair": "USDCAD",
      "entry_time": "2025-09-26 02:00:00+00:00",
      "exit_time": "2025-11-06 15:00:00+00:00",
      "entry_price": 1.394260048866272,
      "exit_price": 1.4128999710083008,
      "position": "short",
      "pnl": -2.002161953766774,
      "pnl_pct": -0.02005356406488051
    },
    {
      "pair": "EURGBP",
      "entry_time": "2023-11-21 22:00:00+00:00",
      "exit_time": "2024-01-30 05:00:00+00:00",
      "entry_price": 0.8702700138092041,
      "exit_price": 0.8517500162124634,
      "position": "long",
      "pnl": -3.19211232770356,
      "pnl_pct": -0.0319211232770356
    },
    {
      "pair": "EURGBP",
      "entry_time": "2024-01-30 05:00:00+00:00",
      "exit_time": "2025-04-11 03:00:00+00:00",
      "entry_price": 0.8517500162124634,
      "exit_price": 0.8699100017547607,
      "position": "short",
      "pnl": -3.1970980320586584,
      "pnl_pct": -0.031981189075376795
    },
    {
      "pair": "EURGBP",
      "entry_time": "2025-04-11 03:00:00+00:00",
      "exit_time": "2025-11-06 15:00:00+00:00",
      "entry_price": 0.8699100017547607,
      "exit_price": 0.8804500102996826,
      "position": "short",
      "pnl": -1.8162696641886569,
      "pnl_pct": -0.018174308589959016
    },
    {
      "pair": "EURJPY",
      "entry_time": "2023-11-22 03:00:00+00:00",
      "exit_time": "2024-04-23 22:00:00+00:00",
      "entry_price": 161.78199768066406,
      "exit_price": 165.65899658203125,
      "position": "short",
      "pnl": -3.5946510955624333,
      "pnl_pct": -0.03594651095562433
    },
    {
      "pair": "EURJPY",
      "entry_time": "2024-04-23 22:00:00+00:00",
      "exit_time": "2024-05-17 03:00:00+00:00",
      "entry_price": 165.65899658203125,
      "exit_price": 169.17300415039062,
      "position": "short",
      "pnl": -3.1807005454464297,
      "pnl_pct": -0.03181844307459001
    },
    {
      "pair": "EURJPY",
      "entry_time": "2024-05-17 03:00:00+00:00",
      "exit_time": "2024-07-01 07:00:00+00:00",
      "entry_price": 169.17300415039062,
      "exit_price": 173.1580047607422,
      "position": "short",
      "pnl": -3.5309717282985518,
      "pnl_pct": -0.035333657078132234
    },
    {
      "pair": "EURJPY",
      "entry_time": "2024-07-01 07:00:00+00:00",
      "exit_time": "2024-08-05 07:00:00+00:00",
      "entry_price": 173.1580047607422,
      "exit_price": 157.0850067138672,
      "position": "short",
      "pnl": 13.909058998619907,
      "pnl_pct": 0.13923408914087074
    },
    {
      "pair": "EURJPY",
      "entry_time": "2024-08-05 07:00:00+00:00",
      "exit_time": "2024-10-31 02:00:00+00:00",
      "entry_price": 157.0850067138672,
      "exit_price": 166.43699645996094,
      "position": "long",
      "pnl": 8.933404164218873,
      "pnl_pct": 0.08930186853983346
    },
    {
      "pair": "EURJPY",
      "entry_time": "2024-10-31 02:00:00+00:00",
      "exit_time": "2024-12-03 12:00:00+00:00",
      "entry_price": 166.43699645996094,
      "exit_price": 157.281005859375,
      "position": "short",
      "pnl": 8.262107169726868,
      "pnl_pct": 0.0825176264472114
    },
    {
      "pair": "EURJPY",
      "entry_time": "2024-12-03 12:00:00+00:00",
      "exit_time": "2024-12-13 22:00:00+00:00",
      "entry_price": 157.281005859375,
      "exit_price": 161.4929962158203,
      "position": "short",
      "pnl": -4.025359452923809,
      "pnl_pct": -0.040170047871622094
    },
    {
      "pair": "EURJPY",
      "entry_time": "2024-12-13 22:00:00+00:00",
      "exit_time": "2025-06-09 14:00:00+00:00",
      "entry_price": 161.4929962158203,
      "exit_price": 164.9720001220703,
      "position": "short",
      "pnl": -3.23683312777502,
      "pnl_pct": -0.032314131149074436
    },
    {
      "pair": "EURJPY",
      "entry_time": "2025-06-09 14:00:00+00:00",
      "exit_time": "2025-09-16 22:00:00+00:00",
      "entry_price": 164.9720001220703,
      "exit_price": 173.83200073242188,
      "position": "long",
      "pnl": 8.066817595224547,
      "pnl_pct": 0.08055913067486281
    },
    {
      "pair": "EURJPY",
      "entry_time": "2025-09-16 22:00:00+00:00",
      "exit_time": "2025-10-30 13:00:00+00:00",
      "entry_price": 173.83200073242188,
      "exit_price": 178.55599975585938,
      "position": "short",
      "pnl": -4.085154803002126,
      "pnl_pct": -0.040763487190506806
    },
    {
      "pair": "EURJPY",
      "entry_time": "2025-10-30 13:00:00+00:00",
      "exit_time": "2025-11-06 15:00:00+00:00",
      "entry_price": 178.55599975585938,
      "exit_price": 176.64199829101562,
      "position": "short",
      "pnl": 1.6107168292569427,
      "pnl_pct": 0.016079001552404635
    },
    {
      "pair": "AUDUSD",
      "entry_time": "2023-11-21 20:00:00+00:00",
      "exit_time": "2024-04-16 04:00:00+00:00",
      "entry_price": 0.6557204723358154,
      "exit_price": 0.6422896385192871,
      "position": "long",
      "pnl": -3.0723839768228163,
      "pnl_pct": -0.03072383976822816
    },
    {
      "pair": "AUDUSD",
      "entry_time": "2024-04-16 04:00:00+00:00",
      "exit_time": "2024-07-11 06:00:00+00:00",
      "entry_price": 0.6422896385192871,
      "exit_price": 0.6756665110588074,
      "position": "long",
      "pnl": 7.792423203246089,
      "pnl_pct": 0.07794818070660343
    },
    {
      "pair": "AUDUSD",
      "entry_time": "2024-07-11 06:00:00+00:00",
      "exit_time": "2024-09-27 11:00:00+00:00",
      "entry_price": 0.6756665110588074,
      "exit_price": 0.6897027492523193,
      "position": "short",
      "pnl": -3.117557949777432,
      "pnl_pct": -0.0311608714442197
    },
    {
      "pair": "AUDUSD",
      "entry_time": "2024-09-27 11:00:00+00:00",
      "exit_time": "2024-10-09 01:00:00+00:00",
      "entry_price": 0.6897027492523193,
      "exit_price": 0.67432701587677,
      "position": "long",
      "pnl": -3.344527187554016,
      "pnl_pct": -0.033439913192061875
    },
    {
      "pair": "AUDUSD",
      "entry_time": "2024-10-09 01:00:00+00:00",
      "exit_time": "2024-12-06 20:00:00+00:00",
      "entry_price": 0.67432701587677,
      "exit_price": 0.6390878558158875,
      "position": "short",
      "pnl": 7.837374243030276,
      "pnl_pct": 0.07838739787489625
    },
    {
      "pair": "AUDUSD",
      "entry_time": "2024-12-06 20:00:00+00:00",
      "exit_time": "2024-12-19 20:00:00+00:00",
      "entry_price": 0.6390878558158875,
      "exit_price": 0.62427818775177,
      "position": "long",
      "pnl": -3.478088710698459,
      "pnl_pct": -0.0347596999286055
    },
    {
      "pair": "AUDUSD",
      "entry_time": "2024-12-19 20:00:00+00:00",
      "exit_time": "2025-02-20 17:00:00+00:00",
      "entry_price": 0.62427818775177,
      "exit_price": 0.6397789120674133,
      "position": "short",
      "pnl": -3.7254500151122687,
      "pnl_pct": -0.0372447523069799
    },
    {
      "pair": "AUDUSD",
      "entry_time": "2025-02-20 17:00:00+00:00",
      "exit_time": "2025-04-04 17:00:00+00:00",
      "entry_price": 0.6397789120674133,
      "exit_price": 0.6033546328544617,
      "position": "short",
      "pnl": 8.538944145278444,
      "pnl_pct": 0.08539890544824719
    },
    {
      "pair": "AUDUSD",
      "entry_time": "2025-04-04 17:00:00+00:00",
      "exit_time": "2025-04-14 08:00:00+00:00",
      "entry_price": 0.6033546328544617,
      "exit_price": 0.633926510810852,
      "position": "long",
      "pnl": 7.606122528682462,
      "pnl_pct": 0.07600474818206487
    },
    {
      "pair": "AUDUSD",
      "entry_time": "2025-04-14 08:00:00+00:00",
      "exit_time": "2025-05-07 01:00:00+00:00",
      "entry_price": 0.633926510810852,
      "exit_price": 0.6498992443084717,
      "position": "short",
      "pnl": -3.7851591299500034,
      "pnl_pct": -0.03779475986228038
    },
    {
      "pair": "AUDUSD",
      "entry_time": "2025-05-07 01:00:00+00:00",
      "exit_time": "2025-09-12 02:00:00+00:00",
      "entry_price": 0.6498992443084717,
      "exit_price": 0.666400134563446,
      "position": "short",
      "pnl": -3.812773295621678,
      "pnl_pct": -0.03808488100151327
    },
    {
      "pair": "AUDUSD",
      "entry_time": "2025-09-12 02:00:00+00:00",
      "exit_time": "2025-11-06 15:00:00+00:00",
      "entry_price": 0.666400134563446,
      "exit_price": 0.6470397710800171,
      "position": "short",
      "pnl": 4.361065785895245,
      "pnl_pct": 0.04357824033779298
    },
    {
      "pair": "GBPCAD",
      "entry_time": "2023-11-22 00:00:00+00:00",
      "exit_time": "2023-12-25 07:00:00+00:00",
      "entry_price": 1.718649983406067,
      "exit_price": 1.6838300228118896,
      "position": "long",
      "pnl": -3.039009769037158,
      "pnl_pct": -0.03039009769037158
    },
    {
      "pair": "GBPCAD",
      "entry_time": "2023-12-25 07:00:00+00:00",
      "exit_time": "2024-07-14 23:00:00+00:00",
      "entry_price": 1.6838300228118896,
      "exit_price": 1.769569993019104,
      "position": "long",
      "pnl": 7.635620512636887,
      "pnl_pct": 0.07637941690578187
    },
    {
      "pair": "GBPCAD",
      "entry_time": "2024-07-14 23:00:00+00:00",
      "exit_time": "2024-09-26 18:00:00+00:00",
      "entry_price": 1.769569993019104,
      "exit_price": 1.8072999715805054,
      "position": "short",
      "pnl": -3.1997028978334647,
      "pnl_pct": -0.03198232794710995
    },
    {
      "pair": "GBPCAD",
      "entry_time": "2024-09-26 18:00:00+00:00",
      "exit_time": "2025-03-04 15:00:00+00:00",
      "entry_price": 1.8072999715805054,
      "exit_price": 1.8434799909591675,
      "position": "short",
      "pnl": -3.003243011367186,
      "pnl_pct": -0.03002823544590297
    },
    {
      "pair": "GBPCAD",
      "entry_time": "2025-03-04 15:00:00+00:00",
      "exit_time": "2025-04-09 20:00:00+00:00",
      "entry_price": 1.8434799909591675,
      "exit_price": 1.80417001247406,
      "position": "long",
      "pnl": -3.1980545634708233,
      "pnl_pct": -0.031985683607545695
    },
    {
      "pair": "GBPCAD",
      "entry_time": "2025-04-09 20:00:00+00:00",
      "exit_time": "2025-11-06 15:00:00+00:00",
      "entry_price": 1.80417001247406,
      "exit_price": 1.8496099710464478,
      "position": "long",
      "pnl": 3.7760959719433793,
      "pnl_pct": 0.03777911027637232
    }
  ]
}